LICENSE
MANIFEST.in
README.md
requirements.txt
setup.py
oxasl_ve/__init__.py
oxasl_ve/_version.py
oxasl_ve/api.py
oxasl_ve/modmat_default.py
oxasl_ve/veaslc_cli_wrapper.py
oxasl_ve.egg-info/PKG-INFO
oxasl_ve.egg-info/SOURCES.txt
oxasl_ve.egg-info/dependency_links.txt
oxasl_ve.egg-info/requires.txt
oxasl_ve.egg-info/top_level.txt
oxasl_ve/wrappers/__init__.py
oxasl_ve/wrappers/veaslc.py